dpat/__init__.py
dpat/exceptions.py
dpat/cli/__init__.py
dpat/cli/convert.py
dpat/cli/create_splits.py
dpat/cli/logging.py
dpat/convert/__init__.py
dpat/convert/hhg.py
dpat/data/__init__.py
dpat/data/dataset.py
dpat/data/datasets.py
dpat/data/transformations.py
dpat/data/transforms.py
dpat/extract_features/__init__.py
dpat/extract_features/datamodules.py
dpat/extract_features/datasets.py
dpat/extract_features/models.py
dpat/extract_features/train.py
dpat/extract_features/transformations.py
dpat/splits/__init__.py
dpat/splits/create_splits.py
dpat/utils/__init__.py
dpat-2.0.0.dist-info/LICENSE
dpat-2.0.0.dist-info/METADATA
dpat-2.0.0.dist-info/WHEEL
dpat-2.0.0.dist-info/entry_points.txt
dpat-2.0.0.dist-info/top_level.txt
dpat-2.0.0.dist-info/RECORD
