Metadata-Version: 2.1
Name: dpat
Version: 2.0.0
Summary: UNKNOWN
Home-page: https://github.com/siemdejong/hhg-dpat
Author: Siem de Jong
Author-email: siem.dejong@hotmail.nl
License: GNU General Public License v3
Keywords: dpat
Platform: UNKNOWN
Classifier: Intended Audience :: Developers
Classifier: License :: OSI Approved :: GNU General Public License v3 (GPLv3)
Classifier: Natural Language :: English
Classifier: Programming Language :: Python :: 3
Classifier: Programming Language :: Python :: 3.9
Requires-Python: >=3.9
License-File: LICENSE
Requires-Dist: dlup (>=0.3)
Requires-Dist: scikit-learn (>=0.24)
